[
  {
    "query": "football world cup",
    "results_count": 5,
    "search_time": 0.0099,
    "timestamp": "2026-05-29 12:57:22"
  },
  {
    "query": "stock market crash",
    "results_count": 5,
    "search_time": 0.0079,
    "timestamp": "2026-05-29 12:58:31"
  },
  {
    "query": "smartphone technology",
    "results_count": 5,
    "search_time": 0.0138,
    "timestamp": "2026-05-29 12:58:33"
  },
  {
    "query": "movie awards ceremony",
    "results_count": 5,
    "search_time": 0.012,
    "timestamp": "2026-05-29 12:58:35"
  },
  {
    "query": "football world cup",
    "results_count": 5,
    "search_time": 0.0198,
    "timestamp": "2026-05-29 13:01:32"
  },
  {
    "query": "world",
    "results_count": 5,
    "search_time": 0.0123,
    "timestamp": "2026-05-29 13:02:08"
  },
  {
    "query": "what",
    "results_count": 0,
    "search_time": 0.0183,
    "timestamp": "2026-05-29 13:02:24"
  },
  {
    "query": "rude",
    "results_count": 4,
    "search_time": 0.0146,
    "timestamp": "2026-05-29 13:02:28"
  },
  {
    "query": "obama",
    "results_count": 0,
    "search_time": 0.0142,
    "timestamp": "2026-05-29 13:02:37"
  },
  {
    "query": "politics",
    "results_count": 5,
    "search_time": 0.0132,
    "timestamp": "2026-05-29 13:02:45"
  },
  {
    "query": "business",
    "results_count": 5,
    "search_time": 0.0206,
    "timestamp": "2026-05-29 13:14:05"
  },
  {
    "query": "business",
    "results_count": 5,
    "search_time": 0.0207,
    "timestamp": "2026-05-29 13:25:30"
  },
  {
    "query": "sport",
    "results_count": 5,
    "search_time": 0.0166,
    "timestamp": "2026-05-29 13:25:36"
  },
  {
    "query": "vidio",
    "results_count": 0,
    "search_time": 0.0221,
    "timestamp": "2026-05-29 13:32:00"
  },
  {
    "query": "america",
    "results_count": 5,
    "search_time": 0.0195,
    "timestamp": "2026-05-29 13:32:08"
  },
  {
    "query": "new york",
    "results_count": 5,
    "search_time": 0.0308,
    "timestamp": "2026-05-29 14:42:25"
  },
  {
    "query": "football",
    "results_count": 5,
    "search_time": 0.0918,
    "timestamp": "2026-05-29 16:42:11"
  },
  {
    "query": "business",
    "results_count": 5,
    "search_time": 0.038,
    "timestamp": "2026-05-29 21:56:38"
  },
  {
    "query": "tech",
    "results_count": 5,
    "search_time": 0.0382,
    "timestamp": "2026-05-29 22:07:35"
  },
  {
    "query": "fact",
    "results_count": 5,
    "search_time": 0.0181,
    "timestamp": "2026-05-29 22:07:52"
  },
  {
    "query": "foootball",
    "results_count": 0,
    "search_time": 0.0266,
    "timestamp": "2026-05-30 17:10:32"
  },
  {
    "query": "foootball",
    "results_count": 0,
    "search_time": 0.0221,
    "timestamp": "2026-05-30 17:10:36"
  },
  {
    "query": "sport",
    "results_count": 5,
    "search_time": 0.0347,
    "timestamp": "2026-06-02 14:38:20"
  },
  {
    "query": "football",
    "results_count": 5,
    "search_time": 0.0375,
    "timestamp": "2026-06-02 19:31:53"
  },
  {
    "query": "fact",
    "results_count": 5,
    "search_time": 0.021,
    "timestamp": "2026-06-02 19:32:08"
  },
  {
    "query": "weak",
    "results_count": 5,
    "search_time": 0.0211,
    "timestamp": "2026-06-02 19:34:48"
  },
  {
    "query": "football",
    "results_count": 5,
    "search_time": 0.0186,
    "timestamp": "2026-06-02 19:54:36"
  },
  {
    "query": "learn",
    "results_count": 5,
    "search_time": 0.017,
    "timestamp": "2026-06-02 19:59:16"
  },
  {
    "query": "word",
    "results_count": 5,
    "search_time": 0.0166,
    "timestamp": "2026-06-02 20:01:38"
  },
  {
    "query": "bisni",
    "results_count": 0,
    "search_time": 0.0176,
    "timestamp": "2026-06-02 20:04:16"
  },
  {
    "query": "learn",
    "results_count": 5,
    "search_time": 0.1133,
    "timestamp": "2026-06-02 20:04:21"
  },
  {
    "query": "world cup",
    "results_count": 5,
    "search_time": 0.0204,
    "timestamp": "2026-06-02 20:09:10"
  },
  {
    "query": "lesson",
    "results_count": 5,
    "search_time": 0.0151,
    "timestamp": "2026-06-02 20:09:55"
  },
  {
    "query": "learn",
    "results_count": 5,
    "search_time": 0.017,
    "timestamp": "2026-06-02 20:10:12"
  },
  {
    "query": "learn",
    "results_count": 5,
    "search_time": 0.0228,
    "timestamp": "2026-06-03 08:58:42"
  },
  {
    "query": "football",
    "results_count": 5,
    "search_time": 0.0319,
    "timestamp": "2026-06-07 20:46:44"
  },
  {
    "query": "learn",
    "results_count": 5,
    "search_time": 0.0189,
    "timestamp": "2026-06-07 20:51:34"
  },
  {
    "query": "hate",
    "results_count": 5,
    "search_time": 0.0304,
    "timestamp": "2026-06-07 20:57:37"
  },
  {
    "query": "what",
    "results_count": 0,
    "search_time": 0.0175,
    "timestamp": "2026-06-07 20:58:37"
  },
  {
    "query": "when",
    "results_count": 0,
    "search_time": 0.0172,
    "timestamp": "2026-06-07 20:58:41"
  },
  {
    "query": "how",
    "results_count": 0,
    "search_time": 0.0172,
    "timestamp": "2026-06-07 20:58:48"
  },
  {
    "query": "last",
    "results_count": 5,
    "search_time": 0.0173,
    "timestamp": "2026-06-07 20:58:54"
  },
  {
    "query": "ball",
    "results_count": 5,
    "search_time": 0.0225,
    "timestamp": "2026-06-07 21:03:56"
  },
  {
    "query": "learn",
    "results_count": 5,
    "search_time": 0.0154,
    "timestamp": "2026-06-07 21:05:24"
  },
  {
    "query": "america",
    "results_count": 5,
    "search_time": 0.0355,
    "timestamp": "2026-06-07 22:07:34"
  },
  {
    "query": "cup",
    "results_count": 5,
    "search_time": 0.0468,
    "timestamp": "2026-06-08 16:53:08"
  }
]